pm2hw/carts/__init__.py
pm2hw/carts/base.py
pm2hw/carts/base_sst.py
pm2hw/carts/dittomini.py
pm2hw/carts/pokecard.py
pm2hw/gui/components/__init__.py
pm2hw/gui/components/gamelist.py
pm2hw/gui/components/help.py
pm2hw/gui/components/library.py
pm2hw/gui/components/linker.py
pm2hw/gui/components/preferences.py
pm2hw/gui/components/status.py
pm2hw/gui/themes/__init__.py
pm2hw/gui/themes/base.py
pm2hw/gui/themes/colorized.py
pm2hw/gui/themes/dark.py
pm2hw/gui/themes/light.py
pm2hw/gui/themes/solarized.py
pm2hw/gui/widgets/__init__.py
pm2hw/gui/widgets/menu.py
pm2hw/gui/widgets/richtext.py
pm2hw/gui/widgets/richtext.pyi
pm2hw/gui/widgets/scrollframe.py
pm2hw/gui/widgets/scrollframe.pyi
pm2hw/gui/__init__.py
pm2hw/gui/__main__.py
pm2hw/gui/i18n.py
pm2hw/gui/resources.py
pm2hw/gui/util.py
pm2hw/info/games/__init__.py
pm2hw/info/games/base.py
pm2hw/info/games/gcn_pchannel.py
pm2hw/info/games/pm_breeder.py
pm2hw/info/games/pm_lunch.py
pm2hw/info/games/pm_party.py
pm2hw/info/games/pm_pichu.py
pm2hw/info/games/pm_pinball.py
pm2hw/info/games/pm_puzzle.py
pm2hw/info/games/pm_puzzle2.py
pm2hw/info/games/pm_race.py
pm2hw/info/games/pm_tetris.py
pm2hw/info/games/pm_togepi.py
pm2hw/info/games/pm_zanycards.py
pm2hw/info/__init__.py
pm2hw/linkers/__init__.py
pm2hw/linkers/base.py
pm2hw/linkers/base_ftdi.py
pm2hw/linkers/dittomini.py
pm2hw/linkers/pokecard.py
pm2hw/locales/en/LC_MESSAGES/pm2hw.mo
pm2hw/locales/ja/LC_MESSAGES/pm2hw.mo
pm2hw/locales/__init__.py
pm2hw/__init__.py
pm2hw/__main__.py
pm2hw/base.py
pm2hw/config.py
pm2hw/exceptions.py
pm2hw/logger.py
pm2hw-0.0.8.dist-info/LICENSE
pm2hw-0.0.8.dist-info/METADATA
pm2hw-0.0.8.dist-info/WHEEL
pm2hw-0.0.8.dist-info/entry_points.txt
resources/add_file.gif
resources/add_folder.gif
resources/remove_file.gif
LICENSE
pm2hw-0.0.8.dist-info/RECORD
