Metadata-Version: 2.1
Name: pm2hw
Version: 0.0.8
Summary: Utility to read and write to all Pokemon mini hardware
Author: Sapphire Becker
Maintainer: Sapphire Becker
Keywords: flash cart,flasher,linker,Pokemon mini
Home-page: https://github.com/logicplace/pm2hw
Project-URL: repository, https://github.com/logicplace/pm2hw
Project-URL: documentation, https://github.com/logicplace/pm2hw
Platform: Windows
Platform: macOS
Platform: Linux
Classifier: Development Status :: 2 - Pre-Alpha
Classifier: Intended Audience :: End Users/Desktop
Classifier: License :: OSI Approved :: Mozilla Public License 2.0 (MPL 2.0)
Classifier: Natural Language :: English
Classifier: Natural Language :: Japanese
Classifier: Operating System :: OS Independent
Classifier: Programming Language :: Python
Classifier: Programming Language :: Python :: 3 :: Only
Classifier: Programming Language :: Python :: 3.7
Classifier: Programming Language :: Python :: 3.8
Classifier: Programming Language :: Python :: 3.9
Classifier: Programming Language :: Python :: 3.10
Classifier: Programming Language :: Python :: Implementation :: CPython
Classifier: Programming Language :: Python :: Implementation :: PyPy
Classifier: Topic :: System :: Emulators
Requires-Python: >=3.7
Requires-Dist: appdirs
Requires-Dist: ftd2xx
Requires-Dist: mistune
Requires-Dist: pyusb
